pyqt5extras/__init__.py
pyqt5extras/animation.py
pyqt5extras/codetextedit.py
pyqt5extras/colorpicker.py
pyqt5extras/dragdropfile.py
pyqt5extras/drop_widgets.py
pyqt5extras/embedwindow.py
pyqt5extras/file_system_widget.py
pyqt5extras/image_tooltip.py
pyqt5extras/imagebox.py
pyqt5extras/requesthandler.py
pyqt5extras/segbtngroup.py
pyqt5extras/spinner.py
pyqt5extras/styledbutton.py
pyqt5extras/syntaxhighlighter.py
pyqt5extras/titlebar.py
pyqt5extras/toast.py
pyqt5extras/toggleswitch.py
pyqt5extras/syntax/cpp.json
pyqt5extras/syntax/python.json
pyqt5extras/themes/default.json
pyqt5extras/themes/monokai.json
pyqt5extras/themes/oceanic.json
pyqt5extras/themes/one-dark.json
pyqt5extras/themes/one-light.json
pyqt5extras/themes/zenburn.json
pyqt5extras-1.0.2.dist-info/DESCRIPTION.rst
pyqt5extras-1.0.2.dist-info/METADATA
pyqt5extras-1.0.2.dist-info/RECORD
pyqt5extras-1.0.2.dist-info/WHEEL
pyqt5extras-1.0.2.dist-info/metadata.json
pyqt5extras-1.0.2.dist-info/top_level.txt
