Metadata-Version: 2.0
Name: pyqt5extras
Version: 1.0.2
Summary: 继承自pyqt5Cumstom的Pyqt5扩展控件
Home-page: https://gitee.com/jiangbin2020/py-project
Author: Peter Jiang
Author-email: 07jiangbin@163.com
License: UNKNOWN
Platform: UNKNOWN
License-File: LICENSE
